injectenv/__init__.py
injectenv/cli.py
injectenv-0.1.3.dist-info/METADATA
injectenv-0.1.3.dist-info/WHEEL
injectenv-0.1.3.dist-info/entry_points.txt
injectenv-0.1.3.dist-info/top_level.txt
injectenv-0.1.3.dist-info/RECORD
