Metadata-Version: 2.4
Name: injectenv
Version: 0.1.3
Summary: Inject env vars into a spawned process.
Requires-Python: >=3.12
Requires-Dist: python-dotenv>=1.0.1
